_pyquat.cpython-39-darwin.so
pyquat/__init__.py
pyquat/plot.py
pyquat/pyquat.c
pyquat/pyquat.h
pyquat/random.py
pyquat/wahba/__init__.py
pyquat/wahba/__init__.pyi
pyquat/wahba/esoq.py
pyquat/wahba/qmethod.py
pyquat/wahba/valenti.py
pyquat-0.5.1.dist-info/LICENSE.txt
pyquat-0.5.1.dist-info/METADATA
pyquat-0.5.1.dist-info/WHEEL
pyquat-0.5.1.dist-info/top_level.txt
pyquat-0.5.1.dist-info/RECORD
